ecr_mirror/__init__.py
ecr_mirror/__main__.py
ecr_mirror-1.3.0.dist-info/WHEEL
ecr_mirror-1.3.0.dist-info/entry_points.txt
ecr_mirror-1.3.0.dist-info/METADATA
ecr_mirror-1.3.0.dist-info/RECORD
