Metadata-Version: 2.1
Name: ecr-mirror
Version: 1.3.0
Summary: Mirror public Docker images to private ECR repositories
License: MIT
Keywords: docker,ecr,mirror
Author: Tom Forbes
Author-email: tom.forbes@onfido.com
Requires-Python: >=3.7,<4.0
Classifier: License :: OSI Approved :: MIT License
Classifier: Programming Language :: Python :: 3
Classifier: Programming Language :: Python :: 3.7
Classifier: Programming Language :: Python :: 3.8
Classifier: Programming Language :: Python :: 3.9
Classifier: Programming Language :: Python :: 3.10
Classifier: Programming Language :: Python :: 3.11
Requires-Dist: boto3
Requires-Dist: boto3-stubs[ecr]
Requires-Dist: click
